bot_station/__init__.py
bot_station/api/__init__.py
bot_station/api/rest/__init__.py
bot_station/api/rest/api.py
bot_station/api/rest/model/__init__.py
bot_station/api/rest/model/bot_call_dto.py
bot_station/api/rest/model/bot_call_result.py
bot_station/api/rest/model/bot_creation_dto.py
bot_station/api/rest/model/bot_creation_result.py
bot_station/api/rest/model/bot_dto.py
bot_station/api/rest/model/bot_train_dto.py
bot_station/api/rest/model/web_app_config.py
bot_station/data/__init__.py
bot_station/data/base/__init__.py
bot_station/data/base/database/UUID.py
bot_station/data/base/database/__init__.py
bot_station/data/base/database/base_db_dto.py
bot_station/data/bot/__init__.py
bot_station/data/bot/chat_message_storage_impl.py
bot_station/data/bot/rag_bot_impl.py
bot_station/data/bot/rag_prompt_samples.py
bot_station/data/bot/model/__init__.py
bot_station/data/bot/model/qdrant_config.py
bot_station/data/bot/model/yandex_cloud_config.py
bot_station/data/bot_station/__init__.py
bot_station/data/bot_station/bot_registry_impl.py
bot_station/data/bot_station/bot_station_impl.py
bot_station/data/bot_station/model/__init__.py
bot_station/data/bot_station/model/bot_info_dto.py
bot_station/data/docs/__init__.py
bot_station/data/docs/qdrant_docs_iterator.py
bot_station/data/docs/qdrant_docs_library.py
bot_station/data/docs/mapper/__init__.py
bot_station/data/docs/mapper/document_mapper.py
bot_station/data/llm/__init__.py
bot_station/data/llm/yandex_gpt_llm.py
bot_station/domain/__init__.py
bot_station/domain/base/__init__.py
bot_station/domain/base/const.py
bot_station/domain/base/utils.py
bot_station/domain/bot/__init__.py
bot_station/domain/bot/bot.py
bot_station/domain/bot/chat_message_storage.py
bot_station/domain/bot/model/__init__.py
bot_station/domain/bot/model/bot_meta_info.py
bot_station/domain/bot/model/lm_call_result.py
bot_station/domain/bot/model/lm_chat_message.py
bot_station/domain/bot_station/__init__.py
bot_station/domain/bot_station/bot_registry.py
bot_station-0.8.0.dist-info/LICENSE
bot_station-0.8.0.dist-info/METADATA
bot_station-0.8.0.dist-info/WHEEL
bot_station-0.8.0.dist-info/top_level.txt
bot_station-0.8.0.dist-info/RECORD
