Metadata-Version: 2.1
Name: bot_station
Version: 0.8.0
Summary: Bot Station SDK + Web App
Author: Maxim Marashan
Classifier: Programming Language :: Python :: 3.10
Classifier: License :: OSI Approved :: MIT License
Classifier: Operating System :: OS Independent
Requires-Python: >=3.10
License-File: LICENSE
Requires-Dist: requests ==2.31.0
Requires-Dist: langchain ==0.1.17
Requires-Dist: langchain-community ==0.0.36
Requires-Dist: qdrant-client ==1.9.1
Requires-Dist: fastembed ==0.2.7
Requires-Dist: yandexcloud ==0.271.0
Requires-Dist: SQLAlchemy ==2.0.29
Requires-Dist: fastapi ==0.110.3
Requires-Dist: uvicorn ==0.29.0
